examples/__init__.py
examples/composite_body.py
examples/edge_enhancement.py
examples/energy_filter.py
examples/experiment.py
examples/fresnel.py
examples/mesh.py
examples/mesh_scan.py
examples/metaballs.py
examples/multigpu.py
examples/paganin.py
examples/propagator.py
examples/simple.py
examples/source.py
examples/source_blur.py
examples/speed.py
examples/tomographic_rotation.py
examples/tomography_4D.py
examples/trajectory.py
examples/transformation.py
examples/transmission_function_sampling.py
examples/util.py
examples/varconvolution.py
syris/__init__.py
syris/config.py
syris/experiments.py
syris/geometry.py
syris/imageprocessing.py
syris/materials.py
syris/math.py
syris/opticalelements.py
syris/physics.py
syris/profiling.py
syris/util.py
syris/bodies/__init__.py
syris/bodies/base.py
syris/bodies/isosurfaces.py
syris/bodies/mesh.py
syris/bodies/simple.py
syris/devices/__init__.py
syris/devices/cameras.py
syris/devices/detectors.py
syris/devices/filters.py
syris/devices/lenses.py
syris/devices/sources.py
syris/devices/data/dimax_quantum_efficiencies.npy
syris/gpu/__init__.py
syris/gpu/multi.py
syris/gpu/util.py
syris/gpu/opencl/heapsort.cl
syris/gpu/opencl/imageprocessing.cl
syris/gpu/opencl/mesh.cl
syris/gpu/opencl/metaobjects.cl
syris/gpu/opencl/physics.cl
syris/gpu/opencl/polynoms_heapsort.cl
syris/gpu/opencl/polyobject.cl
syris/gpu/opencl/rootfinding.cl
syris/gpu/opencl/varconvolution.in
syris/gpu/opencl/vcomplex.cl
syris/gpu/opencl/vfloat_test.cl
syris/groundtruth/__init__.py
syris-0.3.dist-info/LICENSE
syris-0.3.dist-info/METADATA
syris-0.3.dist-info/WHEEL
syris-0.3.dist-info/top_level.txt
syris-0.3.dist-info/RECORD
