Metadata-Version: 2.1
Name: syris
Version: 0.3
Summary: X-ray imaging simulation
Home-page: http://github.com/ufo-kit/syris
Author: Tomas Farago
Author-email: tomas.farago@kit.edu
License: LGPL
Platform: UNKNOWN
Requires-Python: >=3.6
Requires-Dist: imageio
Requires-Dist: matplotlib
Requires-Dist: numpy (>=1.6.1)
Requires-Dist: pyopencl (>=2012.1)
Requires-Dist: quantities (>=0.10.1)
Requires-Dist: reikna
Requires-Dist: scipy (>=0.11.0)
